dnstest/__init__.py
dnstest/__main__.py
dnstest/check.py
dnstest/cli.py
dnstest/matches.py
dnstest/validator.py
dnstest-0.1.0a0.dist-info/LICENSE
dnstest-0.1.0a0.dist-info/WHEEL
dnstest-0.1.0a0.dist-info/METADATA
dnstest-0.1.0a0.dist-info/RECORD
