Metadata-Version: 2.1
Name: dnstest
Version: 0.1.0a0
Summary: A cli tool for testing DNS records match a provided yaml config file
Home-page: https://github.com/leonsmith/dnstest
Keywords: dns,test,dnstest
Author: Leon Smith
Author-email: _@leonmarksmith.com
Requires-Python: >=3.5,<4.0
Classifier: Intended Audience :: Developers
Classifier: License :: OSI Approved :: GNU General Public License v3 (GPLv3)
Classifier: Programming Language :: Python :: 3
Classifier: Programming Language :: Python :: 3.5
Classifier: Programming Language :: Python :: 3.6
Classifier: Programming Language :: Python :: 3.7
Classifier: Topic :: Internet :: Name Service (DNS)
Classifier: Topic :: System :: Monitoring
Classifier: Topic :: Utilities
Requires-Dist: PyYaml (>=5.1,<6.0)
Requires-Dist: cerberus (>=1.2,<2.0)
Requires-Dist: click (>=7.0,<8.0)
Requires-Dist: pydig (>=0.2.0,<0.3.0)
Project-URL: Repository, https://github.com/leonsmith/dnstest
